pycoingecko/__init__.py
pycoingecko/api.py
pycoingecko/utils.py
pycoingecko-3.1.0.dist-info/LICENCE
pycoingecko-3.1.0.dist-info/METADATA
pycoingecko-3.1.0.dist-info/WHEEL
pycoingecko-3.1.0.dist-info/top_level.txt
pycoingecko-3.1.0.dist-info/RECORD
