Metadata-Version: 2.1
Name: pycoingecko
Version: 3.1.0
Summary: Python wrapper around the CoinGecko API
Home-page: https://github.com/man-c/pycoingecko
Author: Christoforou Manolis
Author-email: emchristoforou@gmail.com
License: MIT
Platform: UNKNOWN
Classifier: Programming Language :: Python :: 3
Classifier: Programming Language :: Python :: 2
Classifier: License :: OSI Approved :: MIT License
Classifier: Operating System :: OS Independent
